<annotation>
	<folder>direction</folder>
	<filename>Direction0590.jpg</filename>
	<path>C:\Users\takuya\anaconda3\envs\tf114\keras-yolov3\trans_images\direction\Direction0590.jpg</path>
	<source>
		<database>Unknown</database>
	</source>
	<size>
		<width>640</width>
		<height>480</height>
		<depth>3</depth>
	</size>
	<segmented>0</segmented>
	<object>
		<name>Direction_sign</name>
		<pose>Unspecified</pose>
		<truncated>0</truncated>
		<difficult>0</difficult>
		<bndbox>
			<xmin>373</xmin>
			<ymin>16</ymin>
			<xmax>479</xmax>
			<ymax>113</ymax>
		</bndbox>
	</object>
</annotation>
