<annotation>
	<folder>direction</folder>
	<filename>Direction0560.jpg</filename>
	<path>C:\Users\takuya\anaconda3\envs\tf114\keras-yolov3\trans_images\direction\Direction0560.jpg</path>
	<source>
		<database>Unknown</database>
	</source>
	<size>
		<width>480</width>
		<height>360</height>
		<depth>3</depth>
	</size>
	<segmented>0</segmented>
	<object>
		<name>Direction_sign</name>
		<pose>Unspecified</pose>
		<truncated>0</truncated>
		<difficult>0</difficult>
		<bndbox>
			<xmin>273</xmin>
			<ymin>117</ymin>
			<xmax>308</xmax>
			<ymax>155</ymax>
		</bndbox>
	</object>
	<object>
		<name>Direction_sign</name>
		<pose>Unspecified</pose>
		<truncated>0</truncated>
		<difficult>0</difficult>
		<bndbox>
			<xmin>279</xmin>
			<ymin>62</ymin>
			<xmax>312</xmax>
			<ymax>98</ymax>
		</bndbox>
	</object>
</annotation>
