<annotation>
	<folder>noparking</folder>
	<filename>NoParking0261.jpg</filename>
	<path>C:\Users\takuya\anaconda3\envs\tf114\keras-yolov3\trans_images\noparking\NoParking0261.jpg</path>
	<source>
		<database>Unknown</database>
	</source>
	<size>
		<width>2000</width>
		<height>1500</height>
		<depth>3</depth>
	</size>
	<segmented>0</segmented>
	<object>
		<name>Prohibition_sign</name>
		<pose>Unspecified</pose>
		<truncated>0</truncated>
		<difficult>0</difficult>
		<bndbox>
			<xmin>575</xmin>
			<ymin>53</ymin>
			<xmax>1523</xmax>
			<ymax>1170</ymax>
		</bndbox>
	</object>
</annotation>
