<annotation>
	<folder>noparking</folder>
	<filename>NoParking0352.jpg</filename>
	<path>C:\Users\takuya\anaconda3\envs\tf114\keras-yolov3\trans_images\noparking\NoParking0352.jpg</path>
	<source>
		<database>Unknown</database>
	</source>
	<size>
		<width>640</width>
		<height>478</height>
		<depth>3</depth>
	</size>
	<segmented>0</segmented>
	<object>
		<name>Prohibition_sign</name>
		<pose>Unspecified</pose>
		<truncated>0</truncated>
		<difficult>0</difficult>
		<bndbox>
			<xmin>199</xmin>
			<ymin>126</ymin>
			<xmax>458</xmax>
			<ymax>307</ymax>
		</bndbox>
	</object>
</annotation>
